aio_rom/__init__.py
aio_rom/collections.py
aio_rom/dataclasses.py
aio_rom/exception.py
aio_rom/fields.py
aio_rom/model.py
aio_rom/proxy.py
aio_rom/py.typed
aio_rom/session.py
aio_rom/types.py
aio_rom/utils.py
aio_rom/utils.pyi
aio_rom-0.1.7.dist-info/METADATA
aio_rom-0.1.7.dist-info/WHEEL
aio_rom-0.1.7.dist-info/licenses/LICENSE
aio_rom-0.1.7.dist-info/RECORD
