Metadata-Version: 2.1
Name: aio-rom
Version: 0.1.7
Summary: asyncio based Redis object mapper
Project-URL: Source, https://github.com/fedej/aio-rom
Author-email: fedej <fede_654_87@hotmail.com>
License-Expression: MIT
License-File: LICENSE
Classifier: Development Status :: 4 - Beta
Classifier: Framework :: AsyncIO
Classifier: Intended Audience :: Developers
Classifier: License :: OSI Approved :: MIT License
Classifier: Operating System :: OS Independent
Classifier: Programming Language :: Python
Classifier: Programming Language :: Python :: 3.8
Classifier: Programming Language :: Python :: 3.9
Classifier: Programming Language :: Python :: 3.10
Classifier: Programming Language :: Python :: 3.11
Classifier: Programming Language :: Python :: 3.12
Classifier: Programming Language :: Python :: Implementation :: CPython
Classifier: Programming Language :: Python :: Implementation :: PyPy
Classifier: Topic :: Database :: Front-Ends
Requires-Python: >=3.8
Requires-Dist: redis<5.1.0,>=4.3.4
Requires-Dist: typing-extensions<5.0.4,>=4.4.0
Requires-Dist: wrapt<2.0.0,>=1.14.1
Provides-Extra: dev
Requires-Dist: bandit; extra == 'dev'
Requires-Dist: black; extra == 'dev'
Requires-Dist: flake8; extra == 'dev'
Requires-Dist: flake8-bugbear; extra == 'dev'
Requires-Dist: flake8-comprehensions; extra == 'dev'
Requires-Dist: isort; extra == 'dev'
Requires-Dist: mypy; extra == 'dev'
Requires-Dist: pytest; extra == 'dev'
Requires-Dist: pytest-asyncio; extra == 'dev'
Requires-Dist: pytest-benchmark; extra == 'dev'
